ItIf/ItIf.py
ItIf/__init__.py
ItIf-0.10.dist-info/LICENSE
ItIf-0.10.dist-info/METADATA
ItIf-0.10.dist-info/WHEEL
ItIf-0.10.dist-info/entry_points.txt
ItIf-0.10.dist-info/top_level.txt
ItIf-0.10.dist-info/RECORD
