Metadata-Version: 2.1
Name: ItIf
Version: 0.10
Summary: ItIf provides a convenient and interactive way to transform time signal to frequncy spectra via FFT
Author-email: Luis Bonah <bonah@ph1.uni-koeln.de>
Keywords: FFT,Spectroscopy
Classifier: Programming Language :: Python :: 3
Classifier: License :: OSI Approved :: GNU General Public License v3 (GPLv3)
Classifier: Operating System :: OS Independent
Requires-Python: >=3.7
License-File: LICENSE
Requires-Dist: numpy
Requires-Dist: pandas
Requires-Dist: matplotlib
Requires-Dist: PyQt6
